LICENSE
setup.cfg
setup.py
django_metro_tiny.egg-info/PKG-INFO
django_metro_tiny.egg-info/SOURCES.txt
django_metro_tiny.egg-info/dependency_links.txt
django_metro_tiny.egg-info/not-zip-safe
django_metro_tiny.egg-info/requires.txt
django_metro_tiny.egg-info/top_level.txt
metro_tiny/__init__.py
metro_tiny/admin.py
metro_tiny/models.py
metro_tiny/tests.py
metro_tiny/data/RU/Moscow_ru.txt
metro_tiny/data/RU/Saint_Petersburg_ru.txt
metro_tiny/locale/ru/LC_MESSAGES/django.po
metro_tiny/management/__init__.py
metro_tiny/management/commands/__init__.py
metro_tiny/management/commands/metrotinyimport.py