Metadata-Version: 1.0
Name: django-metro-tiny
Version: 1.0
Summary: Metro stations and lines models for Django
Home-page: http://code.google.com/p/django-metro-tiny/
Author: Konstantin Korikov
Author-email: lostclus@gmail.com
License: MIT
Platform: UNKNOWN
Classifier: Development Status :: 3 - Alpha
Classifier: Environment :: Web Environment
Classifier: Framework :: Django
Classifier: Intended Audience :: Developers
Classifier: License :: OSI Approved :: MIT License
Classifier: Operating System :: OS Independent
Classifier: Programming Language :: Python
Classifier: Programming Language :: Python :: 2
Classifier: Topic :: Internet :: WWW/HTTP
Classifier: Topic :: Software Development :: Libraries :: Python Modules
